Workbook

Sheet Summary & Server Specs
A1: Delhi Police — Infrastructure Requirements: Cross-System Summary & New Server Specification
A2: Comparison across CP Jan Sunwai (CPJS), SHANTI AI Chatbot, the Conference Hall Online Booking System, and PRISM (PHAROS) — compiled 03-Jul-2026 for new server procurement sizing, updated 06-Jul-2026 to add PRISM. SHANTI's GPU spec reflects the 03-Jul-2026 dual-LLM-call correction; see SHANTI sheet Section 2.
A4: 1. System Comparison Matrix
A5: Category | B5: CP Jan Sunwai (CPJS) | C5: SHANTI AI Chatbot | D5: Online Booking System | E5: PRISM
A6: System Type / Architecture | B6: Monolithic FastAPI backend (11 route modules) + self-hosted Ollama LLM microservice; 3-tier (Web / App / DB) | C6: FastAPI backend + IndicBERTv2 embedding + llama.cpp LLM server (Qwen2.5-7B-Instruct); 2 compute components, VM-1/VM-2 | D6: 2-tier: React/Vite frontend + Node.js API (VM-01), PostgreSQL (VM-02) | E6: Multi-tier: React/Vite SPA + Node.js/Express API + PostgreSQL 16 (JSONB) + RabbitMQ event bus + Redis cache + Keycloak (Phase 2 MFA/SSO); 4 compute components
A7: Deployment Scope / Users | B7: ~200 registered users; 40–50 concurrent; Delhi Police PHQ grievance system | C7: ~15,000 msgs/day launch estimate (1,000–4,000 sessions/day); public citizen-facing chatbot | D7: ~15–20 halls; hundreds of department internal users; internal booking tool | E7: Phase 4 target: 18 PS, 10 ACP sub-divisions, 5 DCP districts (approx., ± a few); hierarchical HC→SHO→District/DCP→JCP/ACP→SCP→HQ; internal police users only (~100–120 registered, ~25–35 concurrent)
A8: Public Internet Exposure | B8: Partial — admin/officer access intranet-only; complainant tracking portal via token-protected public URL | C8: Yes — primary citizen-facing endpoint (ports 443/80 public) | D8: No — internal network only (ports 80/443 restricted to internal network) | E8: No — fully internal, role-based hierarchical access; no citizen-facing endpoints
A9: Compute — vCPU (Prod) | B9: ='CP Jan Sunwai (CPJS)'!D40&" cores (API 4 + Ollama 8 + Nginx 2, excl. bastion)" -> 14 cores (API 4 + Ollama 8 + Nginx 2, excl. bastion) | C9: ='SHANTI AI Chatbot'!C53&" cores (VM-1: 8 + VM-2: 8)" -> 16 cores (VM-1: 8 + VM-2: 8) | D9: ='Online Booking System'!C16&" cores (VM-01: 2 + VM-02: 2)" -> 4 cores (VM-01: 2 + VM-02: 2) | E9: =PRISM!C20&" cores (App 8 + Broker/Cache 4 + Identity 4, excl. DB)" -> 16 cores (App 8 + Broker/Cache 4 + Identity 4, excl. DB)
A10: Compute — RAM (Prod) | B10: ='CP Jan Sunwai (CPJS)'!E40&" GB (16 + 32 + 8)" -> 56 GB (16 + 32 + 8) | C10: ='SHANTI AI Chatbot'!D53&" GB (24 + 32)" -> 56 GB (24 + 32) | D10: ='Online Booking System'!D16&" GB (4 + 8)" -> 12 GB (4 + 8) | E10: =PRISM!D20&" GB (16 + 8 + 8)" -> 32 GB (16 + 8 + 8)
A11: GPU Requirement | B11: 1x GPU — SOURCE DATA CONFLICT: 'L4 24GB' vs 'T4 16GB' both cited for the same Ollama transcription VM. Confirm L4 24GB before procurement (CPJS sheet, Section 3 warning). | C11: 1x NVIDIA A10G or L4, 24GB VRAM — REVISED from source doc's T4/16GB (SHANTI sheet, Section 2 & 4: dual-LLM-call workload correction). | D11: None required | E11: None required
A12: Compute VM Local Storage (Prod, SSD/NVMe) | B12: =('CP Jan Sunwai (CPJS)'!F40+'CP Jan Sunwai (CPJS)'!G40)&" GB (OS + additional disk, Prod VMs)" -> 600 GB (OS + additional disk, Prod VMs) | C12: =('SHANTI AI Chatbot'!C68+'SHANTI AI Chatbot'!C69)&" GB (VM-1: 100 + VM-2: 80)" -> 180 GB (VM-1: 100 + VM-2: 80) | D12: ='Online Booking System'!E16&" GB (VM-01: 50 + VM-02: 100)" -> 150 GB (VM-01: 50 + VM-02: 100) | E12: =PRISM!E20&" GB (App 100 + Broker/Cache 60 + Identity 40)" -> 200 GB (App 100 + Broker/Cache 60 + Identity 40)
A13: Database / Object Storage / Backup | B13: ='CP Jan Sunwai (CPJS)'!G50&" GB DB (Prod: Postgres+Redis) + "&'CP Jan Sunwai (CPJS)'!C59&" GB object storage/backup (all envs, incl. DR)" -> 400 GB DB (Prod: Postgres+Redis) + 5100 GB object storage/backup (all envs, incl. DR) | C13: ~5 GB DB (runs on VM-1, already counted above) + 50 GB backup object storage (30-day retention) | D13: Included in VM-02's 100GB (pg_dump backups on same volume, 30-day retention) — no separate object storage tier in source | E13: =PRISM!E25&" GB DB (PostgreSQL 16, self-hosted) + "&PRISM!B39&" GB object storage/backup (MinIO — attachments/evidence + offsite DB backup archive)" -> 400 GB DB (PostgreSQL 16, self-hosted) + 600 GB object storage/backup (MinIO — attachments/evidence + offsite DB backup archive)
A14: Total Provisioned Storage Footprint | B14: =('CP Jan Sunwai (CPJS)'!F40+'CP Jan Sunwai (CPJS)'!G40+'CP Jan Sunwai (CPJS)'!G50+'CP Jan Sunwai (CPJS)'!C59)&" GB (Prod, incl. object/backup)" -> 6100 GB (Prod, incl. object/backup) | C14: =('SHANTI AI Chatbot'!C68+'SHANTI AI Chatbot'!C69+50)&" GB (incl. 50GB backup)" -> 230 GB (incl. 50GB backup) | D14: =('Online Booking System'!E16)&" GB" -> 150 GB | E14: =(PRISM!E20+PRISM!E25+PRISM!B39)&" GB (Prod, incl. DB + object/backup)" -> 1200 GB (Prod, incl. DB + object/backup)
A15: Database Engine(s) | B15: PostgreSQL 16 (pgvector) + Redis 7 | C15: PostgreSQL 15 + Redis 7 + FAISS (file-based) | D15: PostgreSQL 15/16 | E15: PostgreSQL 16 (JSONB) + Redis 7 + RabbitMQ 3.x (message store)
A16: Network Bandwidth | B16: Internal VPN-based access only, no public IP; 500 Mbps NGFW/ALB baseline (Prod) | C16: ~3 GB/month outbound — compute-bound, not network-bound; 100 Mbps sufficient | D16: 100 Mbps standard internal connection sufficient | E16: Internal VPN/WAN-based access only, no public IP; 200 Mbps baseline (Puppeteer PDF rendering & MinIO attachment transfer are main consumers, not general API traffic)
A17: DR / Backup | B17: 50% warm-standby DR; RTO 4h / RPO 1h | C17: Daily pg_dump (30-day retention) + weekly VM snapshots (4 retained); no DR replica at launch | D17: Daily pg_dump (30-day retention); no DR replica specified in source | E17: Daily pg_dump + continuous WAL archiving (append-only audit trail is legally significant — must never be lost); weekly VM snapshots; no warm-standby DR at Phase 2 launch — evaluate ahead of Phase 4 full rollout
A18: Key Bottleneck / Risk | B18: GPU spec conflict in source data (L4 vs T4) for the Ollama transcription VM — confirm before buying | C18: LLM token-generation is the sole bottleneck at all realistic traffic levels; GPU memory bandwidth (not VRAM capacity) is the binding constraint — hence the A10G/L4 upgrade | D18: Low risk — small dataset, low concurrency, no GPU, internal-only network exposure | E18: Puppeteer PDF generation (headless Chromium) is CPU/RAM-bound during report bursts; the Keycloak (MFA/SSO) and MinIO (object storage) tiers are Phase 2 roadmap items not yet deployed in Phase 1 production — provision ahead of Phase 2 go-live
A20: 2. Consolidated Procurement Rollup (New Server Sizing, Prod Environment Only)
A21: Figures below are Prod-only (excl. bastion, UAT, DR) — the footprint that matters for sizing the primary new production server. Each system's own sheet has the full derivation and UAT/DR figures.
A22: Rollup Category | B22: CP Jan Sunwai (CPJS) | C22: SHANTI AI Chatbot | D22: Online Booking System | E22: PRISM (PHAROS)
A23: (a) App/compute VM — vCPU / RAM / local SSD | B23: 14 vCPU / 56 GB / 600 GB | C23: 16 vCPU / 56 GB / 180 GB | D23: 4 vCPU / 12 GB / 150 GB | E23: 16 vCPU / 32 GB / 200 GB
A24: (b) GPU (24GB-VRAM class recommended) | B24: 1x (L4 recommended — confirm) | C24: 1x (A10G or L4) | D24: None | E24: None
A25: (c) DB/PaaS compute — if self-hosted, not managed PaaS | B25: 8 vCPU / 400 GB (Postgres+Redis) | C25: Already counted in (a) — runs on VM-1 | D25: Already counted in (a) — runs on VM-02 | E25: 8 vCPU / 32 GB RAM / 400 GB (PostgreSQL 16)
A26: (d) Object storage / backup tier (separate from compute) | B26: ~3,100 GB | C26: ~50 GB | D26: 0 GB (within VM-02 disk) | E26: =PRISM!B39&" GB" -> 600 GB
A27: TOTAL — (a) compute across all 4 systems | B27: 50 vCPU / 156 GB RAM / 1,130 GB local SSD
A28: TOTAL — (b) GPU across all 4 systems | B28: 2x GPU, 24GB-VRAM class (see risk note below)
A29: TOTAL — (d) object storage / backup across all 4 systems | B29: ~3,750 GB (~3.75 TB)
A31: 3. Recommendation
A32: ✓ NEW SERVER BASELINE (Prod, all 4 systems): ≥50 vCPU / ≥156 GB RAM / ≥1,130 GB NVMe-SSD local compute storage, plus 2x GPU at 24GB VRAM class — 1x A10G/L4 dedicated to SHANTI's LLM server, 1x L4 dedicated to CPJS's Ollama transcription VM (PRISM requires no GPU). Add ~15–20% headroom for CPJS's stated 10% QoQ compute growth, to stay ahead of SHANTI's own 50,000 msgs/day re-scaling trigger, and for PRISM's Phase 3 load-testing target of 250 PS (vs. its ~18 PS/10 ACP/5 DCP Phase 4 rollout figure above) — a practical floor is closer to ~58 vCPU / ~180 GB RAM.
A33: ⚠ Do not assume the two GPU workloads can time-share a single card. CPJS's Ollama VM is scheduled ON only during hearing hours (business hours), but SHANTI is a public, always-on citizen chatbot with no fixed off-hours — the two traffic windows are not guaranteed to be disjoint. Provision 2 separate GPUs (or a dual-GPU server) unless the hearing-hours schedule is confirmed to never overlap chatbot peak traffic. PRISM has no GPU requirement and does not affect this calculation.
A34: Rollup rows (c) and (d) — DB/PaaS compute and object storage/backup — are typically NOT part of a compute server order; they map to managed PaaS (RDS/Azure DB) and S3-compatible object storage respectively. Confirm with NIC Meghraj whether these are procured as separate managed services or must be self-hosted on the same physical hardware; the latter would add CPJS's 8 vCPU / ~3.5 TB and PRISM's 8 vCPU / 400 GB DB requirement, plus the combined ~3.75 TB object-storage/backup tier, onto the server spec above.
A35: This is a first-pass sizing estimate for procurement scoping, built by aggregating each system's own Prod-environment figures (see the CPJS, SHANTI, Online Booking System, and PRISM sheets for full line-item derivation). It excludes UAT/DR capacity — size those separately once the Prod hardware decision is made. Not a substitute for load testing once all four systems are live.

Sheet CP Jan Sunwai (CPJS)
A1: CP Jan Sunwai (CPJS) — Delhi Police Public Grievance System — Infrastructure Detail
A2: Source: NIC Meghraj Cloud Onboarding Questionnaire (CPJS__CP_JAN_SUNWAI__.xlsx) — sheets KYA, Infra Requirements, Drived. Compiled 03-Jul-2026.
A4: 1. Application Profile
A5: Parameter | B5: Value | I5: Remarks
A6: Application type | B6: Monolithic (modular) — single FastAPI process, 11 route modules | I6: Modules: cases, auth, ai_routes, analytics, assignments, tracking, bhashini, notifications, audio, admin, public_sho
A7: Public internet exposure | B7: Partial | I7: Admin/officer access is intranet-only; complainant tracking portal is public via token-protected URL
A8: Current DB size | B8: ~8 GB | I8: PostgreSQL 16 with pgvector extension
A9: Object storage (audio + docs) | B9: ~135 GB/year | I9: Grows with case volume
A10: Data growth (QoQ) | B10: 25%
A11: Compute growth (QoQ) | B11: 10%
A12: User growth (QoQ) | B12: 20%
A13: Total registered users | B13: ~200
A14: Concurrent users | B14: 40–50 (peak 50)
A15: Avg request size | B15: ~40 KB (API) | I15: Most APIs 2–20 KB JSON; live ASR streams 64–128 KB/4-sec chunk; peak uploads (audio/docs) up to ~25 MB
A16: Required IOPS | B16: 10,000 | I16: Department-level aggregate requirement stated in questionnaire
A17: CDN required | B17: Yes
A18: DR required | B18: Yes — 50% of Prod (warm standby) | I18: Can be raised to 100% active-active if near-zero RTO mandated
A19: Environments | B19: Prod, UAT, DR
A20: Email gateway (SMTP) | B20: Required | I20: Transactional email
A21: SMS gateway | B21: Required | I21: OTP identity verification
A23: 2. Third-Party / External Integrations
A24: Integration | B24: Purpose | C24: Protocol | I24: Remarks
A25: Bhashini ASR/NMT | B25: GoI multilingual speech-to-text + translation | C25: REST/HTTPS | I25: Used for JSIO voice-based grievance intake
A26: SMS Gateway | B26: OTP delivery | C26: REST/HTTPS
A27: SMTP Relay | B27: Transactional email | C27: SMTP
A28: Ollama LLM (self-hosted) | B28: AI extraction of structured case fields; IPC/BNS suggestion | C28: Internal REST | I28: Self-hosted internal AI service, not third-party SaaS
A29: Object Storage (S3-compatible) | B29: Audio/document store | C29: REST/HTTPS
A30: All integration is over REST/HTTPS APIs (+ WebSocket for real-time notifications). No direct DB links to external systems — DB is accessed solely by the backend service.
A32: 3. Compute — Virtual Machines (IaaS)
A33: Environment | B33: Layer | C33: Component | D33: No. of VMs | E33: vCPU/VM | F33: RAM/VM (GB) | G33: OS Disk (GB) | H33: Addl. Disk (GB) | I33: Remarks / Instance Class Equivalent
A34: All Envs. | B34: Access | C34: Bastion Host | D34: 1 | E34: 2 | F34: 8 | G34: 100 | H34: 0 | I34: Mandatory access method per NIC Meghraj policy. Separate bastion instance per env (Prod/Dev-UAT/DR) recommended.
A35: Prod Env. | B35: App | C35: CPJS API (Backend) | D35: 1 | E35: 4 | F35: 16 | G35: 100 | H35: 100 | I35: m6i.xlarge / Standard_D4s_v5 — runs FastAPI. IOPS req: 3,000
A36: Prod Env. | B36: App | C36: AI Transcription (Ollama) | D36: 1 | E36: 8 | F36: 32 | G36: 100 | H36: 100 | I36: GPU: g6.xlarge (NVIDIA L4 24GB) / NC8as_T4_v3 — scheduled ON during hearing hours only. IOPS req: 3,000
A37: Prod Env. | B37: Web | C37: Nginx Reverse Proxy | D37: 1 | E37: 2 | F37: 8 | G37: 100 | H37: 100 | I37: Behind ALB + WAF. IOPS req: 1,000
A38: UAT Env. | B38: App | C38: CPJS API (Dev/UAT) | D38: 1 | E38: 2 | F38: 8 | G38: 100 | H38: 100 | I38: Shared Dev+UAT environment. IOPS req: 1,000
A39: DR Env. | B39: App | C39: CPJS API (DR) | D39: 1 | E39: 2 | F39: 8 | G39: 100 | H39: 100 | I39: 50% of Prod capacity — warm standby. IOPS req: 1,500
A40: PROD ONLY — Total (Bastion excl.) | C40: =SUMIF(A34:A39,"Prod Env.",D34:D39) -> 3 | D40: =SUMPRODUCT((A34:A39="Prod Env.")*D34:D39*E34:E39) -> 14 | E40: =SUMPRODUCT((A34:A39="Prod Env.")*D34:D39*F34:F39) -> 56 | F40: =SUMPRODUCT((A34:A39="Prod Env.")*D34:D39*G34:G39) -> 300 | G40: =SUMPRODUCT((A34:A39="Prod Env.")*D34:D39*H34:H39) -> 300
A41: ALL ENVS — Total incl. Bastion, UAT, DR | C41: =SUM(D34:D39) -> 6 | D41: =SUMPRODUCT(D34:D39,E34:E39) -> 20 | E41: =SUMPRODUCT(D34:D39,F34:F39) -> 80 | F41: =SUMPRODUCT(D34:D39,G34:G39) -> 600 | G41: =SUMPRODUCT(D34:D39,H34:H39) -> 500
A42: ⚠ GPU CONFLICT IN SOURCE DATA: the questionnaire's remarks column cites two non-equivalent GPU options for the AI Transcription VM — 'NVIDIA L4 24GB' and 'NC8as_T4_v3' (T4, 16GB). These are not interchangeable (see SHANTI sheet, Section 4, for L4 vs T4 bandwidth analysis). Confirm actual GPU before procurement; L4 24GB is the safer choice for Ollama-served LLM extraction workloads. This VM is scheduled ON only during hearing hours — see Summary sheet for why this should NOT be assumed to time-share with SHANTI's GPU.
A44: 4. Database Requirement (PaaS)
A45: Environment | B45: Database | C45: Version | D45: Count | E45: vCPU | F45: Current Size (GB) | G45: Storage Req. (GB) | H45: IOPS | I45: Remarks
A46: Prod Env. | B46: PostgreSQL | C46: 16 | D46: 1 | E46: 4 | F46: 8 | G46: 200 | H46: 3000 | I46: RDS PostgreSQL 16 / Azure DB PostgreSQL Flexible (D2ds_v5). pgvector for AI semantic search. RAM not specified in source — tied to managed instance class (~16 GB for D2ds_v5-equivalent).
A47: Prod Env. | B47: Redis | C47: 7 | D47: 1 | E47: 4 | F47: 1 | G47: 200 | H47: 1000 | I47: ElastiCache Redis 7 (cache.t4g.small) / Azure Cache Redis Standard C1. Session, OTP, Celery queue. RAM not specified — cache.t4g.small class ≈ 1.37 GB.
A48: Dev Env. | B48: PostgreSQL | C48: 16 | D48: 1 | E48: 4 | F48: 2 | G48: 200 | H48: 1000 | I48: Smaller instance for dev/UAT.
A49: DR Env. | B49: PostgreSQL | C49: 16 | D49: 1 | E49: 4 | F49: 8 | G49: 200 | H49: 1500 | I49: Streaming replica of Prod. Geo-redundant backup. RPO = 1 hr.
A50: PROD ONLY — Total | D50: =SUMIF(A46:A49,"Prod Env.",D46:D49) -> 2 | E50: =SUMIF(A46:A49,"Prod Env.",E46:E49) -> 8 | F50: =SUMIF(A46:A49,"Prod Env.",F46:F49) -> 9 | G50: =SUMIF(A46:A49,"Prod Env.",G46:G49) -> 400 | H50: =SUMIF(A46:A49,"Prod Env.",H46:H49) -> 4000
A52: 5. Additional Storage & Backup Requirement
A53: Environment | B53: Type | C53: Size (GB) | I53: Remarks
A54: Prod Env. | B54: Object Storage | C54: 1000 | I54: Audio recordings + case documents
A55: Prod Env. | B55: Block Storage | C55: 100
A56: DR Env. | B56: Object Storage | C56: 1000
A57: Prod Env. | B57: Backup | C57: 2000 | I57: 1000 (DB) + 1000 (object storage) — OS disk backup mandatory for all VMs/PaaS on NGC
A58: DR Env. | B58: Backup | C58: 1000
A59: TOTAL — Additional + Backup Storage (all envs) | C59: =SUM(C54:C58) -> 5100
A61: 6. Network Services
A62: Service | B62: Unit | C62: Prod | D62: DR | I62: Remarks
A63: Site-to-Site VPN | B63: Per connection/month | C63: 1 | D63: 1 | I63: Primary access path: PHQ intranet ↔ NGC. No public exposure.
A64: Client-to-Site VPN | B64: Per connection/month | C64: 10 | D64: — | I64: Remote admin/officer access
A65: CDN | B65: per GB/month | C65: 1 | D65: 1
A66: Public IP | B66: IP/month | C66: N/A | D66: N/A | I66: No direct public IP exposure — access via ALB/CDN
A67: Load Balancers | B67: Count | C67: 1 (ALB + WAF) | D67: 1 (50% capacity)
A69: 7. Security Services
A70: Service | B70: Unit | C70: Prod | D70: Staging/UAT/Dev | E70: DR | I70: Remarks
A71: Next-Gen Firewall (NGFW) | B71: Throughput (Mbps) | C71: 500 | D71: 50 | E71: 50 | I71: Mandatory for all environments
A72: Application Load Balancer | B72: Throughput (Mbps) | C72: 500 | D72: 50 | E72: 50 | I72: With WAF for public-facing API
A73: Web Application Firewall | B73: Throughput (Mbps) | C73: 100 | D73: Not required | E73: 50 | I73: For production public API endpoint
A74: DDoS Layer 7 | B74: Throughput (Mbps) | C74: 100 | D74: Not required | E74: Not required | I74: For Prod public endpoint
A75: Anti-Malware | B75: License/VM/month | C75: 4 licenses total | I75: 3 Prod VMs + 1 Dev/UAT VM
A76: Vulnerability Scanning | B76: Instances/month | C76: 4 | I76: Same count as anti-malware
A77: SSL Certificate | B77: Per cert/month | C77: Required | D77: Not required | E77: Not required | I77: For .gov.in domain, Prod only
A78: KMS | B78: Keys/month | C78: 2 | D78: 0 | E78: 0 | I78: 1 for DB encryption, 1 for object storage
A79: HSM | B79: Keys/month | C79: 0 | D79: 0 | E79: 0 | I79: Not required at this scale
A80: SIEM | B80: EPS | C80: 100 | D80: 20 | E80: 50
A82: 8. Disaster Recovery / BCP
A83: Parameter | B83: Value | I83: Remarks
A84: DR capacity | B84: 50% of Prod (warm standby) | I84: Can raise to 100% active-active if near-zero RTO mandated
A85: RTO (Recovery Time Objective) | B85: 4 hours
A86: RPO (Recovery Point Objective) | B86: 1 hour
A87: Data sync — initial | B87: 1 TB (PostgreSQL ≤1000 GB + object storage) | I87: Then continuous async delta replication (DB WAL + object-store)
A88: Data sync — change rate | B88: ~25% QoQ growth
A89: Backup automation | B89: Daily automated RDS/Azure DB backups + geo-redundant object storage snapshots
A90: Risk profile | B90: Low | I90: Small dataset, fully cloud-managed services
A92: Sizing basis: current on-premise PHQ prototype migrating to National Government Cloud (NGC/Meghraj) for production. Concurrent users 40-50, IOPS requirement 10,000 (department aggregate). Deployed as IaaS VMs + PaaS managed DB/cache.

Sheet SHANTI AI Chatbot
A1: S.H.A.N.T.I. — Delhi Police Citizen Services Chatbot — Infrastructure Detail
A2: Source: SHANTI_Infrastructure_Requirements.pdf (29-Jun-2026). REVISED 03-Jul-2026 for the dual-LLM-call workload pattern confirmed in query_pipeline.py — see Section 2. All other figures are as-published in the source document.
A4: 1. Scale Assumptions (Source, Unchanged)
A5: Parameter | B5: Estimate | I5: Basis / Rationale
A6: Delhi Police website — daily visitors | B6: 30,000 – 80,000 | I6: Typical mid-tier state government portal
A7: Chatbot adoption rate | B7: 3 – 5% | I7: Standard for a new, non-mandatory feature
A8: Daily chatbot sessions | B8: 1,000 – 4,000 | I8: Conservative launch estimate
A9: Messages per session (avg) | B9: 4 – 6 | I9: Based on current guided flow depth
A10: Daily messages — working figure | B10: ~15,000 | I10: Used for all calculations in this document
A11: Peak hour multiplier | B11: 4 – 5x | I11: Morning 9–11 AM, afternoon 2–4 PM
A12: Peak messages per minute | B12: 15 – 25 | I12: Derived from daily figure and peak multiplier
A13: Message payload size (req + resp) | B13: 3 – 8 KB | I13: Text-only; no media or file transfers
A15: 2. Workload Correction — Dual LLM Call Pattern (Deviation From Source PDF)
A16: ⚠ Every user message triggers TWO sequential LLM calls, not one: decompose_query() then generate_answer() (query_pipeline.py:104, query_pipeline.py:362). The source PDF's Component B sizing (Section 4) implicitly assumed one short call per message — this doubles the real LLM call volume behind the 15,000 msgs/day figure in Section 1.
A17: ⚠ The generate_answer() call also carries a real context load: merge_and_diversify_context() fills up to a 3,500-token budget of retrieved chunks, plus prompt scaffolding — so each generation call is realistically prompting with ~4,000–4,500 tokens, not a short message. This is heavier than the 'quick citizen query' assumption baked into the source PDF's 16GB-card KV-cache sizing.
A18: Net effect: Component B (LLM server, Section 4) and the Recommended VM Configuration (Section 5) below are re-sized for 2x real LLM calls/message at ~4,000–4,500 tokens of context per generation call. Sections 1, 3, and 6–11 are unchanged from the source PDF — the correction only touches GPU selection, not vCPU/RAM/storage/DB/OS/network figures.
A20: 3. Compute Requirement — Component A: Application Server (FastAPI + IndicBERTv2)
A21: IndicBERTv2 is loaded into RAM at startup and held resident. Every incoming request triggers one forward pass for semantic embedding (unaffected by the dual-LLM-call correction — embedding runs once per message, not twice). FastAPI is async and handles concurrent requests efficiently with multiple worker processes.
A22: Resource | B22: Requirement | I22: Rationale
A23: vCPU | B23: 8 cores | I23: FastAPI async workers; handles 20–30 concurrent requests comfortably
A24: RAM | B24: 24 GB | I24: IndicBERTv2 ~1.2GB + PyTorch overhead ~4GB + worker processes ~4GB + OS/headroom ~4GB
A25: GPU | B25: Not required at this scale | I25: Embedding inference at 15–25 RPM peak runs acceptably on CPU
A27: 4. Compute Requirement — Component B: LLM Server (llama.cpp + Qwen2.5-7B-Instruct) — REVISED
A28: This is the critical performance bottleneck. The LLM generates one token at a time and cannot be trivially parallelised beyond the n_parallel slots configured in llama.cpp. GPU inference is mandatory for acceptable response latency in a citizen-facing deployment — now doubly so given the 2x call load per message established in Section 2.
A29: Resource | B29: Requirement | I29: Rationale
A30: vCPU | B30: 8 cores | I30: llama.cpp uses CPU for tokenisation and pre/post-processing even in GPU mode. Unchanged from source.
A31: RAM | B31: 32 GB | I31: ~16GB for model layers offloaded to system RAM + OS overhead + buffer. Unchanged from source.
A33: GPU / VRAM sizing — recalculated for the corrected workload (n_parallel raised from 4 to 8 to absorb the 2x call load, ~4,000–4,500 token context per generation call):
A34: VRAM Component | B34: Size | I34: Notes
A35: Qwen2.5-7B-Instruct, Q4_K_M GGUF | B35: ~4.4 GB | I35: Base model weights, VRAM-resident
A36: KV cache, ~4,500 token context, n_parallel=4 (fp16) | B36: ~1 – 1.5 GB | I36: Source PDF's original sizing assumption — short prompt, n_parallel=4
A37: KV cache, same context, n_parallel=8 (to absorb the 2x call load) | B37: ~2.5 – 3 GB | I37: Needed to keep peak latency in check once decompose_query()+generate_answer() are counted as 2 calls/message
A38: CUDA runtime / engine overhead | B38: ~1 – 1.5 GB | I38: llama.cpp + CUDA context
A39: Realistic total, n_parallel=8 | B39: ~9 – 10 GB | I39: Comfortably fits in a 16GB card with room to spare
A40: The model itself comfortably fits in 16GB — the source PDF's 16GB (T4) recommendation is not wrong on VRAM capacity. But capacity is not the same as speed: token-generation speed is bounded by memory bandwidth, not VRAM size. That is where this sheet deviates from the source PDF's GPU choice.
A42: GPU | B42: VRAM | C42: Mem. Bandwidth | I42: Notes
A43: T4 (source PDF's option) | B43: 16 GB | C43: ~320 GB/s | I43: Older (Turing, 2018). Runs the workload, but noticeably slower tokens/sec — risky against the p95 > 8s latency alert threshold (Section 10) once 2x LLM calls/message are counted at peak load.
A44: A10G | B44: 24 GB | C44: ~600 GB/s | I44: Nearly 2x T4's bandwidth. Comfortable headroom for higher n_parallel and longer contexts as the corpus grows.
A45: L4 | B45: 24 GB | C45: ~300 GB/s raw, but Ada-generation efficiency | I45: Much better quantized-inference efficiency than T4 despite a similar raw bandwidth number. Best perf/cost for this workload (small quantized model, INT4/INT8-friendly); increasingly the default GPU for LLM inference on major clouds.
A46: A100 40GB | B46: 40 GB | C46: ~1.5 TB/s | I46: Overkill at 15,000 msgs/day; only justified once the source PDF's own 50,000 msgs/day re-scaling trigger (Section 11) is crossed.
A47: ✓ RECOMMENDATION: 1x NVIDIA A10G or L4, 24GB VRAM — NOT the T4/16GB in the source PDF. Same logic as the source PDF's own 'GPU inference is non-negotiable' stance: the real workload is already 2x heavier via query decomposition, so buy the bandwidth headroom now rather than re-provisioning the moment adoption ticks up.
A49: 5. Recommended VM Configuration — REVISED
A50: VM | B50: Role | C50: vCPU | D50: RAM (GB) | E50: GPU | I50: Remarks
A51: VM-1 | B51: FastAPI + IndicBERTv2 + Nginx + PostgreSQL + Redis | C51: 8 | D51: 24 | E51: None
A52: VM-2 | B52: llama.cpp LLM server (Qwen2.5-7B-Instruct) | C52: 8 | D52: 32 | E52: 1x A10G or L4 — 24GB VRAM
A53: TOTAL | C53: =SUM(C51:C52) -> 16 | D53: =SUM(D51:D52) -> 56 | E53: 24GB VRAM (1x GPU, revised)
A54: Alternative (per source PDF): single VM with 16 vCPU, 64GB RAM, 1x A10G/L4 24GB — simpler ops but single point of failure. Two-VM setup is preferred for independent scaling and maintenance without full downtime.
A56: 6. Storage Requirement (Source, Unchanged — GB Figures Not Affected by the Correction)
A57: VM | B57: Item | C57: Size (GB) | I57: Notes
A58: VM-1 | B58: OS — Ubuntu Server 22.04 LTS | C58: 20 | I58: Base system installation
A59: VM-1 | B59: Python 3.11 + venv + dependencies (PyTorch, Transformers, FastAPI) | C59: 8 | I59: PyTorch CUDA build alone ~2.5GB
A60: VM-1 | B60: IndicBERTv2 model (weights + tokenizer) | C60: 1.2 | I60: Loaded from local /model directory at startup
A61: VM-1 | B61: Application code + services.json + FAISS index | C61: 0.5 | I61: Negligible; included for completeness
A62: VM-1 | B62: PostgreSQL feedback database (3-yr growth) | C62: 5 | I62: ~15,000 sessions/day x 365 x 3 yrs x ~300 bytes/record
A63: VM-1 | B63: Nginx access logs (1yr, rotated + compressed) | C63: 15 | I63: ~2KB/request x 15,000/day x 365 days
A64: VM-1 | B64: Application + system logs | C64: 5 | I64: Rotating w/ logrotate, compressed after 7 days. Expect a modest increase vs. source PDF since 2x LLM calls/message roughly doubles per-message log lines — still well within the 100GB provisioned envelope.
A65: VM-1 | B65: System swap | C65: 8 | I65: Required for CPU-offload spikes during LLM inference
A66: VM-2 | B66: Qwen2.5-7B-Instruct Q4_K_M GGUF | C66: 4.5 | I66: Served by llama.cpp; single file
A67: VM-2 | B67: OS + CUDA 12.1 + cuDNN + Python/PyTorch(CUDA) + llama.cpp build | C67: ~29.5 (not itemized in source) | I67: Balance of the ~34GB VM-2 raw total; source PDF does not break this out further
A68: Total — VM-1 (App server), provisioned | C68: 100 | I68: Provision 100GB NVMe SSD for headroom & growth (raw usage ~55GB)
A69: Total — VM-2 (LLM server), provisioned | C69: 80 | I69: Provision 80GB NVMe SSD (raw usage ~34GB)
A70: An additional 50GB of object storage (e.g. NIC S3-compatible) is recommended for database backups with 30-day retention. Use NVMe SSD on both VMs — spinning disk (HDD) increases llama.cpp startup time from ~8s to ~45s and degrades FAISS index load performance.
A72: 7. Database Requirement
A73: The current implementation uses flat JSON files for feedback and session data. These are not suitable for a production citizen-facing deployment. The following database components are required.
A74: Component | B74: Solution | C74: Purpose | I74: Sizing
A75: Feedback & sessions | B75: PostgreSQL 15 | C75: Structured storage of user feedback, session metadata, and audit logs | I75: 2 vCPU, 4GB RAM; ~5GB over 3 years. Can run on VM-1 — no dedicated DB VM needed at this scale (already inside VM-1's 8 vCPU / 24GB envelope).
A76: Rate limiting state | B76: Redis 7 | C76: In-memory per-IP request counting with automatic key expiry | I76: 512MB RAM; negligible disk
A77: FAISS index | B77: File-based (retain) | C77: Read-only at runtime; loaded once at startup; no DB overhead needed | I77: ~50MB file
A78: services.json catalog | B78: File-based (retain) | C78: 45 service records; loaded once at startup; updated via deployment | I78: ~50KB file
A79: Operational notes: Daily pg_dump to object storage with 30-day retention is sufficient; no replication required at launch. Connection pooling via PgBouncer recommended once daily sessions exceed 5,000.
A81: 8. Operating System & Software Dependencies
A82: Layer | B82: Component | C82: Version | I82: Notes
A83: Operating System | B83: Ubuntu Server 22.04 LTS | C83: 22.04 | I83: 5-year LTS; NIC Meghraj compatible; government-standard Linux
A84: Runtime | B84: Python | C84: 3.11.x | I84: Required for FastAPI, Transformers, and all ML dependencies
A85: GPU / CUDA | B85: CUDA Toolkit | C85: 12.1 | I85: Required on VM-2 for GPU-accelerated LLM inference
A86: GPU / CUDA | B86: cuDNN | C86: 8.9.x | I86: Deep learning primitives; required by PyTorch CUDA build
A87: ML Framework | B87: PyTorch (CUDA) | C87: 2.2.x | I87: Runs IndicBERTv2 via HuggingFace Transformers
A88: LLM Server | B88: llama.cpp | C88: Latest stable | I88: Compiled with LLAMA_CUDA=1; serves Qwen2.5-7B on GPU
A89: Web Framework | B89: FastAPI | C89: 0.111.x | I89: ASGI framework; runs via Uvicorn workers
A90: ASGI Server | B90: Uvicorn | C90: 0.29.x | I90: 4 workers recommended; managed by systemd
A91: Reverse Proxy | B91: Nginx | C91: 1.24.x | I91: SSL termination, rate limiting, static file serving, upstream proxy
A92: TLS Certificates | B92: Certbot / Let's Encrypt | C92: Latest | I92: Or NIC CA certificate if hosted under gov.in domain
A93: Database | B93: PostgreSQL | C93: 15.x | I93: Feedback storage; managed by systemd
... A98: Monitoring | B98: Prometheus + Grafana | C98: Latest stable | I98: GPU metrics, request latency, disk, memory; optional but recommended
A100: 9. Network, Ports, Bandwidth & Security
A101: Port | B101: Service | C101: Exposed To | I101: Rule
A102: 443 | B102: Nginx — HTTPS | C102: Public internet | I102: Primary citizen-facing endpoint; TLS 1.2+ only
A103: 80 | B103: Nginx — HTTP | C103: Public internet | I103: Redirect to 443 only; no content served over HTTP
A104: 8000 | B104: FastAPI / Uvicorn | C104: VM-1 internal only | I104: Never exposed to internet; Nginx proxies to this
A105: 8080 | B105: llama.cpp LLM server | C105: VM-1 to VM-2 internal subnet only | I105: CRITICAL: must be firewalled; exposes raw LLM access if public
A106: 5432 | B106: PostgreSQL | C106: VM-1 internal only | I106: Loopback or VPC internal; no external access
A107: 6379 | B107: Redis | C107: VM-1 internal only | I107: Loopback only; bind 127.0.0.1 in redis.conf
A108: 22 | B108: SSH | C108: VPN / jump host only | I108: Key-based auth; root login disabled; restricted to admin IP range
A110: Traffic Type | B110: Daily Volume | C110: Monthly Volume | I110: Notes
A111: Inbound — user messages (~1KB avg) | B111: ~15 MB | C111: ~450 MB
A112: Outbound — bot replies + service cards (~5KB avg) | B112: ~75 MB | C112: ~2.25 GB
A113: Total citizen-facing traffic | B113: ~90 MB/day | C113: ~3 GB/month
A114: Internal VM-1 to VM-2 (LLM requests) | B114: ~30 MB | C114: ~900 MB
A115: Bandwidth is negligible for this system — the bottleneck is compute (LLM inference latency), not network throughput. A 100 Mbps uplink is far more than sufficient. No CDN is required for the API; a CDN may be used for the frontend static assets.
A117: Security Requirement | B117: Implementation
...

Sheet Online Booking System
A1: Conference Hall Booking & Management System — Infrastructure Detail
A2: Source: Infrastructure Requirements Report — Conference Hall Booking & Management System, Delhi Police (prepared 30-Jun-2026). Compiled 03-Jul-2026, unchanged from source.
A4: 1. Application Profile & Deployment Scope
A5: Parameter | B5: Value | I5: Remarks
A6: Architecture | B6: 2-Tier (separated application & database servers)
A7: Deployment scope classification | B7: Internal | I7: ~15–20 halls, hundreds of department internal users only
A8: Public internet exposure | B8: No | I8: Ports 80/443 open to internal network only — not the public internet
A9: Frontend | B9: React (compiled static files, Vite build) | I9: Served by Nginx / IIS
A10: Backend | B10: Node.js API | I10: Hosted on VM-01 alongside the frontend
A12: 2. Compute — Virtual Machines
A13: VM | B13: Component | C13: vCPU | D13: RAM (GB) | E13: Storage (GB SSD) | I13: Remarks
A14: VM-01 | B14: Application Server — hosts React frontend (static files) & Node.js backend API | C14: 2 | D14: 4 | E14: 50
A15: VM-02 | B15: Database Server — dedicated PostgreSQL instance & automated backup storage | C15: 2 | D15: 8 | E15: 100
A16: TOTAL | C16: =SUM(C14:C15) -> 4 | D16: =SUM(D14:D15) -> 12 | E16: =SUM(E14:E15) -> 150
A17: Rationale for separation: isolating the database on a dedicated VM ensures that traffic spikes or application-level issues on VM-01 cannot exhaust database resources, preventing cascading failures.
A19: 3. Storage Allocation Summary (Total: 150 GB)
A20: VM | B20: Capacity | C20: Usage Breakdown
A21: VM-01 (App Server) SSD | B21: 50 GB | C21: OS installation, Node.js runtime, application code (<500MB), PM2 process logs, Nginx access/error logs accumulated over time.
A22: VM-02 (DB Server) SSD | B22: 100 GB | C22: OS installation, PostgreSQL data files, daily pg_dump backup archives (30-day retention), Write-Ahead Logs (WAL), and headroom for OS/DB updates over a 3–5 year lifecycle.
A24: 4. Database Requirement
A25: Parameter | B25: Specification
A26: Engine | B26: PostgreSQL — version 15 or 16 (LTS)
A27: Target database | B27: delhi_police_halls
A28: Dedicated DB user | B28: conference_app_user — restricted read/write access; no superuser or DDL privileges
A29: Automated backups | B29: Daily scheduled pg_dump exports with a 30-day rolling retention period
A31: 5. Operating System & Software Dependencies
A32: Component | B32: Specification | I32: Notes
A33: Operating System (Preferred) | B33: Ubuntu 22.04 LTS / 24.04 LTS | I33: Ubuntu recommended for this stack; Windows or Windows Server 2022 available if required by department policy
A34: Runtime | B34: Node.js v24.x (LTS) | I34: Required for the backend API server
A35: Process Manager | B35: PM2 | I35: Keeps the Node.js process running continuously; configured to auto-restart on server reboot
A36: Web Server / Reverse Proxy | B36: Nginx (Linux) or IIS (Windows) | I36: Serves compiled React/Vite static files and proxies /api requests to the Node.js backend
A38: 6. Network, Ports, Bandwidth & Security
A39: VM | B39: Port | C39: Protocol | I39: Access Rule
A40: VM-01 App Server | B40: 80 | C40: HTTP | I40: Open to internal network — auto-redirects to HTTPS (443)
A41: VM-01 App Server | B41: 443 | C41: HTTPS | I41: Open to internal network — primary application access
A42: VM-01 App Server | B42: 22 / 3389 | C42: SSH / RDP | I42: Restricted strictly to IT Admin team IP addresses only
A43: VM-02 DB Server | B43: 5432 | C43: PostgreSQL | I43: Strictly restricted. Only VM-01 (App Server IP) and the DB Administrator's IP are permitted. No general internal or public access.
A44: Bandwidth: a standard 100 Mbps internal network connection is sufficient given the low concurrent-user profile of this deployment.
A46: 7. Additional Infrastructure Requirements
A47: Requirement | B47: Details
A48: Internal DNS entry | B48: A human-readable hostname mapped to VM-01's IP address. Example: conference.hq.local or vimarsh.delhipolice.gov.in
A49: SSL / TLS certificate | B49: To be issued by the internal IT department Certificate Authority (CA) for the assigned DNS entry, enabling full HTTPS encryption in transit.
A50: SMTP relay (email server) | B50: The following details are required from the department's internal mail infrastructure to enable automated OTP dispatch and booking confirmation emails: SMTP host/relay server address, SMTP port (typically 25, 465, or 587), authentication credentials (if required), sender address/display name to be used.
A52: 8. Summary — Infrastructure at a Glance
A53: Requirement | B53: Specification
A54: VMs | B54: 2 (Application server + Database server) — 2-tier architecture
A55: vCPU — total | B55: 4 cores (2 + 2)
A56: RAM — total | B56: 12 GB (4 GB + 8 GB)
A57: GPU | B57: None required
A58: Storage — total | B58: 150 GB SSD (50 GB VM-01 + 100 GB VM-02)
A59: Primary database | B59: PostgreSQL 15/16 (delhi_police_halls)
A60: Operating system | B60: Ubuntu 22.04/24.04 LTS (preferred) or Windows Server 2022
A61: Bandwidth | B61: 100 Mbps internal network — sufficient for low concurrent-user profile
A62: Public ports | B62: None — 80/443 open to internal network only
A63: Deployment scope | B63: ~15–20 halls; hundreds of department internal users only
A65: Source: Infrastructure Requirements Report — Conference Hall Booking & Management System, Delhi Police, prepared 30-Jun-2026. All figures reproduced as-published; no corrections were required for this system.

Sheet PRISM
A1: PRISM (PHAROS) — Police Hierarchical Automated Reporting & Operations System — Infrastructure Detail
A2: Source: PRISM (PHAROS) project specification (CLAUDE.md) and current codebase (backend/frontend package.json, docker-compose.yml). Compiled 06-Jul-2026 for the same procurement-sizing exercise as the CPJS, SHANTI, and Online Booking System sheets. Phase 1 (JWT auth, RBAC, 3 record types, HC→SHO→District workflow) is live; figures below size for Phase 2 (active) and note Phase 3/4 scaling triggers where relevant.
A4: 1. Application Profile & Deployment Scope
A5: Parameter | B5: Value | I5: Remarks
A6: Architecture | B6: Multi-tier: React/Vite SPA + Node.js/Express API + PostgreSQL 16 (JSONB) + RabbitMQ event bus + Redis cache | I6: Modules never call each other directly — all cross-module communication goes through the RabbitMQ 'pharos' topic exchange (Event Bus Isolation pillar)
A7: Deployment scope classification | B7: Internal — Delhi Police hierarchy (HC → SHO → District Officer/DCP → JCP/ACP → SCP → HQ) | I7: Phase 4 target: 18 PS, 10 ACP sub-divisions, 5 DCP districts (approx., ± a few) rollout; architecture load-tested per Phase 3 roadmap for 250 PS full-scale deployment
A9: Public internet exposure | B9: No | I9: Fully internal, role-based hierarchical access only — no citizen-facing endpoints
A10: Frontend | B10: React 19 + Vite, Ant Design, Tailwind CSS (compiled static build) | I10: Served by Nginx; English/Hindi i18n baked in (label_en/label_hi on every field)
A11: Backend | B11: Node.js / Express (ES Modules) — 12+ route modules (auth, records, fields, workflow, compilation, analytics, reports, audit, admin, notifications, upload, users) | I11: REST API, dual-registered at /api/v1/ and /api/
A12: Event bus | B12: RabbitMQ (topic exchange 'pharos') | I12: auditHandler subscribes 'record.*' → writes record_revisions; notifyHandler subscribes status-change/compilation events
A13: Report generation | B13: Puppeteer (headless Chromium) — PDF + CSV, async job queue (report_jobs) | I13: CPU/RAM-intensive per report; isolated as background jobs on the app tier, not inline with request handling
A15: 2. Compute — Virtual Machines
A16: VM | B16: Component | C16: vCPU | D16: RAM (GB) | E16: Storage (GB SSD) | I16: Remarks
A17: VM-01 | B17: Application Server — Node.js/Express API + Nginx (React/Vite static build) + Puppeteer PDF/CSV report workers | C17: 8 | D17: 16 | E17: 100 | I17: Puppeteer spawns headless Chromium per report job — sized for concurrent report generation without starving the API
A18: VM-02 | B18: Message Broker & Cache — RabbitMQ (event bus) + Redis (session/rate-limit cache) | C18: 4 | D18: 8 | E18: 60 | I18: RabbitMQ topic exchange 'pharos' is the sole cross-module communication path (Event Bus Isolation pillar)
A19: VM-03 | B19: Identity Server — Keycloak (MFA/SSO) | C19: 4 | D19: 8 | E19: 40 | I19: Phase 2 roadmap item (Section 14: Keycloak/MFA) — not yet deployed in Phase 1 production; provision ahead of Phase 2 go-live
A20: TOTAL (compute, excl. DB) | C20: =SUM(C17:C19) -> 16 | D20: =SUM(D17:D19) -> 32 | E20: =SUM(E17:E19) -> 200
A21: Rationale for separation: the message-broker/cache tier and the identity/MFA tier are isolated from the API tier so RabbitMQ throughput, Redis load, or Keycloak/MinIO I/O cannot starve the primary request path — consistent with the Event Bus Isolation architecture pillar. The database is sized separately in Section 3 since it may be procured as managed PaaS rather than self-hosted compute.
A23: 3. Database Requirement
A24: Component | B24: Engine | C24: vCPU | D24: RAM (GB) | E24: Storage (GB SSD) | I24: Remarks
A25: DB Server | B25: PostgreSQL 16 | C25: 8 | D25: 32 | E25: 400 | I25: JSONB dynamic records (Dynamic Field Registry pillar) + append-only record_revisions/audit_logs (never purged); storage sized for multi-year retention growth
A27: Parameter | B27: Specification
A28: Target database | B28: pharos_db
A29: Core tables (12) | B29: hierarchy_nodes, users, field_registry, records, record_revisions, workflow_transitions, audit_logs, compilations, report_jobs, notifications, custom_field_definitions, custom_field_values
A30: Data model | B30: Schema-stable — new fields added via field_registry inserts, not ALTER TABLE (Dynamic Field Registry pillar)
A31: Dedicated DB user | B31: pharos_app_user — restricted read/write access; no superuser or DDL privileges
A32: Automated backups | B32: Daily pg_dump + continuous WAL archiving — the append-only audit trail must never be lost (Append-only Audit pillar)
A33: Migrations | B33: node scripts/migrations.js — idempotent (CREATE TABLE IF NOT EXISTS)
A35: 4. Additional Storage & Backup Requirement
A36: Type | B36: Size (GB) | I36: Remarks
A37: Object storage (MinIO / S3-compatible) | B37: 500 | I37: Uploaded attachments/evidence documents & photos across all onboarded PS (upload module) — Phase 2 roadmap item
A38: Backup (offsite pg_dump archive) | B38: 100 | I38: Encrypted offsite copy of daily DB backups, distinct from the on-VM backup staging already counted in Section 3
A39: TOTAL — Additional + Backup Storage | B39: =SUM(B37:B38) -> 600
A41: 5. Storage Allocation Summary (Total Provisioned: 1,200 GB)
A42: Tier | B42: Capacity | C42: Usage Breakdown
A43: VM-01 (App Server) SSD | C43: 100 GB
A44: VM-02 (Broker/Cache) SSD | C44: 60 GB
A45: VM-03 (Identity) SSD | C45: 40 GB
A46: DB Server SSD | C46: 400 GB
A47: Object Storage & Backup (MinIO) | C47: 600 GB
A49: 6. Operating System & Software Dependencies
A50: Component | B50: Specification | I50: Notes
A51: Operating System (Preferred) | B51: Ubuntu 22.04 LTS / 24.04 LTS | I51: Consistent across all VMs
A52: Runtime | B52: Node.js v20.x LTS | I52: Backend API (ES Modules, "type": "module")
A53: Process Manager | B53: PM2 or systemd | I53: Auto-restarts the Express API and event-handler processes on reboot
A54: Web Server / Reverse Proxy | B54: Nginx | I54: Serves the compiled React/Vite build; proxies /api to Express
A55: Message Broker | B55: RabbitMQ 3.x (management plugin) | I55: Topic exchange 'pharos'; management UI restricted to admin IPs
A56: Cache / Session Store | B56: Redis 7.x | I56: ioredis client
A57: Headless Browser | B57: Chromium (via Puppeteer) | I57: PDF report generation — requires Devanagari-capable fonts for Hindi (label_hi) rendering
A58: Identity Provider | B58: Keycloak (Phase 2) | I58: MFA/SSO — provision ahead of Phase 2 rollout
A59: Object Storage | B59: MinIO (Phase 2) | I59: S3-compatible; attachment/evidence storage
A61: 7. Network, Ports, Bandwidth & Security
A62: VM | B62: Port | C62: Protocol | I62: Access Rule
A63: VM-01 App Server | B63: 80 | C63: HTTP | I63: Internal Delhi Police network / VPN only — redirects to HTTPS (443)
A64: VM-01 App Server | B64: 443 | C64: HTTPS | I64: Internal network / VPN — primary application access for all hierarchy levels
A65: VM-01 App Server | B65: 22 | C65: SSH | I65: Restricted strictly to IT Admin team IP addresses only
A66: DB Server | B66: 5432 | C66: PostgreSQL | I66: Restricted to VM-01 (App Server IP) and the DB Administrator's IP only — no general internal or public access
A67: VM-02 Broker/Cache | B67: 5672 | C67: AMQP | I67: Restricted to VM-01 — RabbitMQ publish/subscribe traffic only
A68: VM-02 Broker/Cache | B68: 15672 | C68: HTTP (Mgmt UI) | I68: Restricted to IT Admin team IPs only
A69: VM-02 Broker/Cache | B69: 6379 | C69: Redis | I69: Restricted to VM-01
A70: VM-03 Identity | B70: 8080 / 8443 | C70: HTTP/HTTPS (Keycloak) | I70: Restricted to VM-01 and IT Admin team IPs
A71: Bandwidth: internal VPN/WAN-based access only, no public IP; 200 Mbps recommended baseline — Puppeteer PDF generation and MinIO attachment transfer are the main bandwidth consumers, not general API traffic.
A73: 8. Additional Infrastructure Requirements
A74: Requirement | B74: Details
A75: Internal DNS entry | B75: Human-readable hostname mapped to VM-01's IP address. Example: prism.delhipolice.gov.in or pharos.hq.local
A76: SSL / TLS certificate | B76: To be issued by the internal IT department Certificate Authority (CA) for the assigned DNS entry, enabling full HTTPS encryption in transit
A77: VPN / network access | B77: All VMs reachable only over the Delhi Police internal WAN/VPN — no public IP on any tier
A78: Bilingual rendering support | B78: Puppeteer PDF worker (VM-01) requires Devanagari-capable fonts installed for Hindi (label_hi) report rendering
A79: Load testing | B79: Phase 3 roadmap item — validate the spec below at 250 PS scale before full district rollout (Phase 4)
A81: 9. Summary — Infrastructure at a Glance
A82: Requirement | B82: Specification
A83: VMs | B83: 4 (Application + Message Broker/Cache + Identity + Database) — 4-tier architecture
A84: vCPU — compute total (excl. DB) | B84: 16 cores (8 + 4 + 4)
A85: RAM — compute total (excl. DB) | B85: 32 GB (16 + 8 + 8)
A86: GPU | B86: None required
A87: Database compute | B87: 8 vCPU / 32 GB RAM (PostgreSQL 16, self-hosted or managed PaaS)
A88: Storage — compute VMs | B88: 200 GB SSD (100 + 60 + 40)
A89: Storage — database | B89: 400 GB SSD
A90: Storage — object storage / backup | B90: 600 GB (500 MinIO + 100 offsite backup)
A91: Total provisioned storage | B91: 1,200 GB (200 compute + 400 DB + 600 object/backup)
A92: Primary database | B92: PostgreSQL 16 (pharos_db)
A93: Operating system | B93: Ubuntu 22.04 / 24.04 LTS
... A96: Deployment scope | B96: Phase 4 target: 18 PS, 10 ACP sub-divisions, 5 DCP districts (approx., ± a few); architecture validated (Phase 3 roadmap) for 250 PS full-scale deployment
A98: Source: PRISM (PHAROS) project specification (CLAUDE.md) and current codebase (backend/frontend package.json, docker-compose.yml), compiled 06-Jul-2026. VM-03 (Keycloak/MFA) and the MinIO object-storage tier reflect Phase 2 roadmap requirements not yet deployed in Phase 1 production — provision ahead of Phase 2 go-live. This is a first-pass sizing estimate for procurement scoping, not a substitute for load testing once Phase 2 is live.
